setup.py
dsnd_dsitributions_pri/Binomialdistribution.py
dsnd_dsitributions_pri/Gaussiandistribution.py
dsnd_dsitributions_pri/Generaldistribution.py
dsnd_dsitributions_pri/__init__.py
dsnd_dsitributions_pri.egg-info/PKG-INFO
dsnd_dsitributions_pri.egg-info/SOURCES.txt
dsnd_dsitributions_pri.egg-info/dependency_links.txt
dsnd_dsitributions_pri.egg-info/not-zip-safe
dsnd_dsitributions_pri.egg-info/top_level.txt